logger/__init__.py
logger/logger.py
logger_henryriveracs-0.3.1.dist-info/LICENSE
logger_henryriveracs-0.3.1.dist-info/METADATA
logger_henryriveracs-0.3.1.dist-info/WHEEL
logger_henryriveracs-0.3.1.dist-info/top_level.txt
logger_henryriveracs-0.3.1.dist-info/RECORD
