Metadata-Version: 2.1
Name: logger-henryriveracs
Version: 0.3.1
Summary: A native python3 logging module for quickly setting up and managing logs.
Author-email: Henry Rivera <henry@wheatrevolution.com>
License: MIT License        
Project-URL: Homepage, https://github.com/henryriveraCS/logger
Project-URL: Bug Tracker, https://github.com/henryriveraCS/logger/issues
Classifier: Programming Language :: Python :: 3
Classifier: License :: OSI Approved :: MIT License
Classifier: Operating System :: OS Independent
Requires-Python: >=3.6
License-File: LICENSE
